rlmodule/__init__.py
rlmodule/skrl/__init__.py
rlmodule/skrl/torch/__init__.py
rlmodule/skrl/torch/examples/gymnasium/cnn_experimental.py
rlmodule/skrl/torch/examples/gymnasium/pendulum_ppo_mlp_separate_model.py
rlmodule/skrl/torch/examples/gymnasium/pendulum_ppo_mlp_shared_model.py
rlmodule/skrl/torch/examples/gymnasium/pendulum_ppo_rnn_forwarded_input_shared_model.py
rlmodule/skrl/torch/examples/gymnasium/pendulum_ppo_rnn_separate_model.py
rlmodule/skrl/torch/examples/gymnasium/pendulum_ppo_rnn_shared_model.py
rlmodule/skrl/torch/examples/gymnasium/pendulum_sac_mlp_separate_model.py
rlmodule/skrl/torch/examples/gymnasium/skrl_no_module.py
rlmodule/skrl/torch/examples/gymnasium/skrl_no_module_rnn.py
rlmodule/skrl/torch/examples/gymnasium/skrl_sac.py
rlmodule/skrl/torch/examples/gymnasium/temp.py
rlmodule/skrl/torch/network/__init__.py
rlmodule/skrl/torch/output_layer/__init__.py
rlmodule/source/__init__.py
rlmodule/source/build.py
rlmodule/source/log_std.py
rlmodule/source/log_std_cfg.py
rlmodule/source/model.py
rlmodule/source/network.py
rlmodule/source/network_cfg.py
rlmodule/source/output_layer.py
rlmodule/source/output_layer_cfg.py
rlmodule/source/rlmodel.py
rlmodule/source/rlmodel_cfg.py
rlmodule/source/utils.py
rlmodule/source/nvidia_utils/__init__.py
rlmodule/source/nvidia_utils/configclass.py
rlmodule/source/nvidia_utils/dict.py
rlmodule/source/nvidia_utils/string.py
rlmodule-0.1.6.3.dist-info/LICENSE
rlmodule-0.1.6.3.dist-info/METADATA
rlmodule-0.1.6.3.dist-info/WHEEL
rlmodule-0.1.6.3.dist-info/top_level.txt
rlmodule-0.1.6.3.dist-info/RECORD
